LICENSE.txt
MANIFEST.in
README.md
README.rst
requires.txt
setup.py
robotx/__init__.py
robotx.egg-info/PKG-INFO
robotx.egg-info/SOURCES.txt
robotx.egg-info/dependency_links.txt
robotx.egg-info/entry_points.txt
robotx.egg-info/requires.txt
robotx.egg-info/top_level.txt
robotx/conf/__init__.py
robotx/core/__init__.py
robotx/core/base.py
robotx/core/distlistener.py
robotx/core/exceptions.py
robotx/core/fabworker.py
robotx/core/generator.py
robotx/core/listener.py
robotx/core/nitrateclient.py
robotx/core/paramshandler.py
robotx/core/predistribute.py
robotx/core/resultvistor.py
robotx/core/workerdaemon.py
robotx/core/commands/__init__.py
robotx/core/commands/check.py
robotx/core/commands/debug.py
robotx/core/commands/generate.py
robotx/core/commands/run.py
robotx/lib/DebugLibrary.py
robotx/lib/SeleniumExt.py
robotx/lib/XML-RPC.py
robotx/lib/__init__.py
robotx/lib/seleniumext/__init__.py
robotx/lib/seleniumext/keywords/__init__.py
robotx/lib/seleniumext/keywords/_actionchains.py
robotx/lib/seleniumext/keywords/_draganddrop.py
robotx/lib/seleniumext/keywords/_pagetests.py
robotx/template/__init__.py
robotx/template/project_template/cases/01__webui/01__wiki_test.txt
robotx/template/project_template/cases/02__cmd/01__gherkin.txt
robotx/template/project_template/doc/testsoso_cases_doc.html
robotx/template/project_template/doc/resource_docs/cmd_res.html
robotx/template/project_template/doc/resource_docs/common_res.html
robotx/template/project_template/doc/resource_docs/home_page.html
robotx/template/project_template/doc/resource_docs/ride_page.html
robotx/template/project_template/doc/resource_docs/wiki_robot_page.html
robotx/template/project_template/others/__init__.py
robotx/template/project_template/resources/CalculatorLibrary.py
robotx/template/project_template/resources/calculator.py
robotx/template/project_template/resources/cmd_res.txt
robotx/template/project_template/resources/common_res.txt
robotx/template/project_template/resources/home_page.txt
robotx/template/project_template/resources/ride_page.txt
robotx/template/project_template/resources/wiki_robot_page.txt
robotx/template/project_template/results/__init__.py
