Metadata-Version: 1.0
Name: robotx
Version: 0.2.2
Summary: Toolset for automation development with Robot Framework
Home-page: https://github.com/idumpling/robotx/
Author: Xin Gao
Author-email: fdumpling@gmail.com
License: MIT
Platform: UNKNOWN
